{
  "openapi": "3.0.0",
  "info": {
    "title": "Cisco-IOS-XE-ignition-oper",
    "description": "This module contains a collection of YANG definitions\n     for Ignition Power Management operational data.\n     Copyright (c) 2021-2022, 2025 by Cisco Systems, Inc.\n     All rights reserved.\n\nCisco IOS-XE operational state data (read-only).\n**Category:** Other Services\n**Paths:** 2",
    "version": "17.18.1"
  },
  "servers": [
    {
      "url": "https://{device}/restconf",
      "variables": {
        "device": {
          "default": "router.example.com",
          "description": "Device IP or hostname"
        }
      }
    }
  ],
  "paths": {
    "/data/Cisco-IOS-XE-ignition-oper:ignition-oper-data": {
      "get": {
        "summary": "Get ignition-oper-data",
        "description": "Operational state of Ignition Power",
        "operationId": "get-ignition-oper-data-0",
        "tags": [
          "Cisco-IOS-XE-ignition-oper"
        ],
        "responses": {
          "200": {
            "description": "Success",
            "content": {
              "application/yang-data+json": {
                "schema": {
                  "$ref": "#/components/schemas/Cisco-IOS-XE-ignition-oper-ignition-oper-data"
                }
              }
            }
          },
          "404": {
            "description": "Resource not found"
          },
          "401": {
            "description": "Unauthorized"
          }
        }
      }
    },
    "/data/Cisco-IOS-XE-ignition-oper:ignition-oper-data/ignition-status": {
      "get": {
        "summary": "Get ignition-status",
        "description": "Ignition Power Management",
        "operationId": "get-ignition-status-1",
        "tags": [
          "Cisco-IOS-XE-ignition-oper"
        ],
        "responses": {
          "200": {
            "description": "Success",
            "content": {
              "application/yang-data+json": {
                "schema": {
                  "$ref": "#/components/schemas/Cisco-IOS-XE-ignition-oper-ignition-status"
                }
              }
            }
          },
          "404": {
            "description": "Resource not found"
          },
          "401": {
            "description": "Unauthorized"
          }
        }
      }
    }
  },
  "components": {
    "securitySchemes": {
      "basicAuth": {
        "type": "http",
        "scheme": "basic"
      }
    },
    "schemas": {
      "Cisco-IOS-XE-ignition-oper-ignition-oper-data": {
        "type": "object",
        "properties": {
          "ignition-mgmt": {
            "type": "string",
            "description": "Ignition Management status"
          },
          "input-volt": {
            "type": "number",
            "description": "Ignition Input Voltage"
          },
          "pwr-state": {
            "type": "string",
            "description": "Ignition power status"
          },
          "sense": {
            "type": "string",
            "description": "Ignition voltage sense state"
          },
          "shutdown-time": {
            "type": "string",
            "description": "Time when ignition power will be shutdown"
          },
          "undervoltage": {
            "type": "number",
            "description": "Under voltage threshold"
          },
          "overvoltage": {
            "type": "number",
            "description": "Over voltage threshold"
          },
          "undervoltage-time-delay": {
            "type": "integer",
            "minimum": 0,
            "maximum": 255,
            "description": "Amount of time device remains powered on before\n         shutdown due to ignition under voltage"
          },
          "overvoltage-time-delay": {
            "type": "integer",
            "minimum": 0,
            "maximum": 255,
            "description": "Amount of time device remains powered on before\n         shutdown due to ignition over voltage"
          },
          "ignition-off-time-delay": {
            "type": "integer",
            "minimum": 0,
            "maximum": 65535,
            "description": "Amount of time device remains powered on after\n         ignition off"
          },
          "battery-type": {
            "type": "string",
            "description": "Ignition battery type"
          },
          "sense-on-threshold": {
            "type": "number",
            "description": "When input voltage is greater than this ignition\n         sense threshold, it powers on the device"
          },
          "sense-off-threshold": {
            "type": "number",
            "description": "When input voltage is lower than this ignition\n         sense threshold, it powers off the device"
          },
          "ignition-status": {
            "type": "object",
            "properties": {
              "ignition-mgmt": {
                "type": "string",
                "description": "Ignition Management status"
              },
              "input-volt": {
                "type": "number",
                "description": "Ignition Input Voltage"
              },
              "pwr-state": {
                "type": "string",
                "description": "Ignition power status"
              },
              "sense": {
                "type": "string",
                "description": "Ignition voltage sense state"
              },
              "shutdown-time": {
                "type": "string",
                "description": "Time when ignition power will be shutdown"
              },
              "undervoltage": {
                "type": "number",
                "description": "Under voltage threshold"
              },
              "overvoltage": {
                "type": "number",
                "description": "Over voltage threshold"
              },
              "undervoltage-time-delay": {
                "type": "integer",
                "minimum": 0,
                "maximum": 255,
                "description": "Amount of time device remains powered on before\n         shutdown due to ignition under voltage"
              },
              "overvoltage-time-delay": {
                "type": "integer",
                "minimum": 0,
                "maximum": 255,
                "description": "Amount of time device remains powered on before\n         shutdown due to ignition over voltage"
              },
              "ignition-off-time-delay": {
                "type": "integer",
                "minimum": 0,
                "maximum": 65535,
                "description": "Amount of time device remains powered on after\n         ignition off"
              },
              "battery-type": {
                "type": "string",
                "description": "Ignition battery type"
              },
              "sense-on-threshold": {
                "type": "number",
                "description": "When input voltage is greater than this ignition\n         sense threshold, it powers on the device"
              },
              "sense-off-threshold": {
                "type": "number",
                "description": "When input voltage is lower than this ignition\n         sense threshold, it powers off the device"
              }
            },
            "description": "Ignition Power Management"
          }
        }
      },
      "Cisco-IOS-XE-ignition-oper-ignition-status": {
        "type": "object",
        "properties": {
          "ignition-mgmt": {
            "type": "string",
            "description": "Ignition Management status"
          },
          "input-volt": {
            "type": "number",
            "description": "Ignition Input Voltage"
          },
          "pwr-state": {
            "type": "string",
            "description": "Ignition power status"
          },
          "sense": {
            "type": "string",
            "description": "Ignition voltage sense state"
          },
          "shutdown-time": {
            "type": "string",
            "description": "Time when ignition power will be shutdown"
          },
          "undervoltage": {
            "type": "number",
            "description": "Under voltage threshold"
          },
          "overvoltage": {
            "type": "number",
            "description": "Over voltage threshold"
          },
          "undervoltage-time-delay": {
            "type": "integer",
            "minimum": 0,
            "maximum": 255,
            "description": "Amount of time device remains powered on before\n         shutdown due to ignition under voltage"
          },
          "overvoltage-time-delay": {
            "type": "integer",
            "minimum": 0,
            "maximum": 255,
            "description": "Amount of time device remains powered on before\n         shutdown due to ignition over voltage"
          },
          "ignition-off-time-delay": {
            "type": "integer",
            "minimum": 0,
            "maximum": 65535,
            "description": "Amount of time device remains powered on after\n         ignition off"
          },
          "battery-type": {
            "type": "string",
            "description": "Ignition battery type"
          },
          "sense-on-threshold": {
            "type": "number",
            "description": "When input voltage is greater than this ignition\n         sense threshold, it powers on the device"
          },
          "sense-off-threshold": {
            "type": "number",
            "description": "When input voltage is lower than this ignition\n         sense threshold, it powers off the device"
          }
        }
      }
    }
  },
  "security": [
    {
      "basicAuth": []
    }
  ],
  "tags": [
    {
      "name": "Cisco-IOS-XE-ignition-oper",
      "description": "This module contains a collection of YANG definitions\n     for Ignition Power Management operational data.\n     Copyright (c) 2021-2022, 2025 by Cisco Systems, Inc.\n     All rights reserved."
    }
  ]
}