{
  "openapi": "3.0.0",
  "info": {
    "title": "Cisco-IOS-XE-scada-gw-oper",
    "description": "This module contains a collection of YANG definitions\n     for Scada Gateway operational data.\n     Copyright (c) 2019, 2022 by Cisco Systems, Inc.\n     All rights reserved.\n\nCisco IOS-XE operational state data (read-only).\n**Category:** Other Services\n**Paths:** 3",
    "version": "17.18.1"
  },
  "servers": [
    {
      "url": "https://{device}/restconf",
      "variables": {
        "device": {
          "default": "router.example.com",
          "description": "Device IP or hostname"
        }
      }
    }
  ],
  "paths": {
    "/data/Cisco-IOS-XE-scada-gw-oper:scada-gw-oper-data": {
      "get": {
        "summary": "Get scada-gw-oper-data",
        "description": "Operational state of Scada Gateway",
        "operationId": "get-scada-gw-oper-data-0",
        "tags": [
          "Cisco-IOS-XE-scada-gw-oper"
        ],
        "responses": {
          "200": {
            "description": "Success",
            "content": {
              "application/yang-data+json": {
                "schema": {
                  "$ref": "#/components/schemas/Cisco-IOS-XE-scada-gw-oper-scada-gw-oper-data"
                }
              }
            }
          },
          "404": {
            "description": "Resource not found"
          },
          "401": {
            "description": "Unauthorized"
          }
        }
      }
    },
    "/data/Cisco-IOS-XE-scada-gw-oper:scada-gw-oper-data/scada-gw-stats": {
      "get": {
        "summary": "Get scada-gw-stats",
        "description": "Scada Gateway operation statistics",
        "operationId": "get-scada-gw-stats-1",
        "tags": [
          "Cisco-IOS-XE-scada-gw-oper"
        ],
        "responses": {
          "200": {
            "description": "Success",
            "content": {
              "application/yang-data+json": {
                "schema": {
                  "$ref": "#/components/schemas/Cisco-IOS-XE-scada-gw-oper-scada-gw-stats"
                }
              }
            }
          },
          "404": {
            "description": "Resource not found"
          },
          "401": {
            "description": "Unauthorized"
          }
        }
      }
    },
    "/data/Cisco-IOS-XE-scada-gw-oper:scada-gw-oper-data/scada-gw-conns": {
      "get": {
        "summary": "Get scada-gw-conns",
        "description": "Scada Gateway Connections",
        "operationId": "get-scada-gw-conns-2",
        "tags": [
          "Cisco-IOS-XE-scada-gw-oper"
        ],
        "responses": {
          "200": {
            "description": "Success",
            "content": {
              "application/yang-data+json": {
                "schema": {
                  "$ref": "#/components/schemas/Cisco-IOS-XE-scada-gw-oper-scada-gw-conns"
                }
              }
            }
          },
          "404": {
            "description": "Resource not found"
          },
          "401": {
            "description": "Unauthorized"
          }
        }
      }
    }
  },
  "components": {
    "securitySchemes": {
      "basicAuth": {
        "type": "http",
        "scheme": "basic"
      }
    },
    "schemas": {
      "Cisco-IOS-XE-scada-gw-oper-scada-gw-oper-data": {
        "type": "object",
        "properties": {
          "channel-name": {
            "type": "string",
            "description": "Name of the channel"
          },
          "messages-sent": {
            "type": "integer",
            "minimum": 0,
            "maximum": 4294967295,
            "description": "Total messages sent on the channel"
          },
          "messages-received": {
            "type": "integer",
            "minimum": 0,
            "maximum": 4294967295,
            "description": "Total messages received on the channel"
          },
          "timeouts": {
            "type": "integer",
            "minimum": 0,
            "maximum": 4294967295,
            "description": "Total timeouts"
          },
          "aborts": {
            "type": "integer",
            "minimum": 0,
            "maximum": 4294967295,
            "description": "Total number of aborts"
          },
          "rejections": {
            "type": "integer",
            "minimum": 0,
            "maximum": 4294967295,
            "description": "Total rejections"
          },
          "protocol-errors": {
            "type": "integer",
            "minimum": 0,
            "maximum": 4294967295,
            "description": "Total protocol errors"
          },
          "link-errors": {
            "type": "integer",
            "minimum": 0,
            "maximum": 4294967295,
            "description": "Total link errors"
          },
          "addr-errors": {
            "type": "integer",
            "minimum": 0,
            "maximum": 4294967295,
            "description": "Total address errors"
          },
          "local-ip": {
            "type": "string",
            "description": "Local IP used by the TCP connection"
          },
          "local-port": {
            "type": "integer",
            "minimum": 0,
            "maximum": 65535,
            "description": "Local port used by the TCP connection"
          },
          "remote-ip": {
            "type": "string",
            "description": "Remote IP of the TCP connection"
          },
          "data-socket": {
            "type": "integer",
            "minimum": 0,
            "maximum": 4294967295,
            "description": "Data socket associated with the TCP connection"
          },
          "scada-gw-stats": {
            "type": "object",
            "properties": {
              "channel-name": {
                "type": "string",
                "description": "Name of the channel"
              },
              "messages-sent": {
                "type": "integer",
                "minimum": 0,
                "maximum": 4294967295,
                "description": "Total messages sent on the channel"
              },
              "messages-received": {
                "type": "integer",
                "minimum": 0,
                "maximum": 4294967295,
                "description": "Total messages received on the channel"
              },
              "timeouts": {
                "type": "integer",
                "minimum": 0,
                "maximum": 4294967295,
                "description": "Total timeouts"
              },
              "aborts": {
                "type": "integer",
                "minimum": 0,
                "maximum": 4294967295,
                "description": "Total number of aborts"
              },
              "rejections": {
                "type": "integer",
                "minimum": 0,
                "maximum": 4294967295,
                "description": "Total rejections"
              },
              "protocol-errors": {
                "type": "integer",
                "minimum": 0,
                "maximum": 4294967295,
                "description": "Total protocol errors"
              },
              "link-errors": {
                "type": "integer",
                "minimum": 0,
                "maximum": 4294967295,
                "description": "Total link errors"
              },
              "addr-errors": {
                "type": "integer",
                "minimum": 0,
                "maximum": 4294967295,
                "description": "Total address errors"
              }
            },
            "description": "Scada Gateway operation statistics"
          },
          "scada-gw-conns": {
            "type": "object",
            "properties": {
              "local-ip": {
                "type": "string",
                "description": "Local IP used by the TCP connection"
              },
              "local-port": {
                "type": "integer",
                "minimum": 0,
                "maximum": 65535,
                "description": "Local port used by the TCP connection"
              },
              "remote-ip": {
                "type": "string",
                "description": "Remote IP of the TCP connection"
              },
              "data-socket": {
                "type": "integer",
                "minimum": 0,
                "maximum": 4294967295,
                "description": "Data socket associated with the TCP connection"
              },
              "channel-name": {
                "type": "string",
                "description": "Name of the channel"
              }
            },
            "description": "Scada Gateway Connections"
          }
        }
      },
      "Cisco-IOS-XE-scada-gw-oper-scada-gw-stats": {
        "type": "object",
        "properties": {
          "channel-name": {
            "type": "string",
            "description": "Name of the channel"
          },
          "messages-sent": {
            "type": "integer",
            "minimum": 0,
            "maximum": 4294967295,
            "description": "Total messages sent on the channel"
          },
          "messages-received": {
            "type": "integer",
            "minimum": 0,
            "maximum": 4294967295,
            "description": "Total messages received on the channel"
          },
          "timeouts": {
            "type": "integer",
            "minimum": 0,
            "maximum": 4294967295,
            "description": "Total timeouts"
          },
          "aborts": {
            "type": "integer",
            "minimum": 0,
            "maximum": 4294967295,
            "description": "Total number of aborts"
          },
          "rejections": {
            "type": "integer",
            "minimum": 0,
            "maximum": 4294967295,
            "description": "Total rejections"
          },
          "protocol-errors": {
            "type": "integer",
            "minimum": 0,
            "maximum": 4294967295,
            "description": "Total protocol errors"
          },
          "link-errors": {
            "type": "integer",
            "minimum": 0,
            "maximum": 4294967295,
            "description": "Total link errors"
          },
          "addr-errors": {
            "type": "integer",
            "minimum": 0,
            "maximum": 4294967295,
            "description": "Total address errors"
          }
        }
      },
      "Cisco-IOS-XE-scada-gw-oper-scada-gw-conns": {
        "type": "object",
        "properties": {
          "local-ip": {
            "type": "string",
            "description": "Local IP used by the TCP connection"
          },
          "local-port": {
            "type": "integer",
            "minimum": 0,
            "maximum": 65535,
            "description": "Local port used by the TCP connection"
          },
          "remote-ip": {
            "type": "string",
            "description": "Remote IP of the TCP connection"
          },
          "data-socket": {
            "type": "integer",
            "minimum": 0,
            "maximum": 4294967295,
            "description": "Data socket associated with the TCP connection"
          },
          "channel-name": {
            "type": "string",
            "description": "Name of the channel"
          }
        }
      }
    }
  },
  "security": [
    {
      "basicAuth": []
    }
  ],
  "tags": [
    {
      "name": "Cisco-IOS-XE-scada-gw-oper",
      "description": "This module contains a collection of YANG definitions\n     for Scada Gateway operational data.\n     Copyright (c) 2019, 2022 by Cisco Systems, Inc.\n     All rights reserved."
    }
  ]
}